ws_copy_policy/__init__.py
ws_copy_policy/_version.py
ws_copy_policy/copy_policy.py
ws_copy_policy-23.12.2.dist-info/LICENSE
ws_copy_policy-23.12.2.dist-info/METADATA
ws_copy_policy-23.12.2.dist-info/WHEEL
ws_copy_policy-23.12.2.dist-info/entry_points.txt
ws_copy_policy-23.12.2.dist-info/top_level.txt
ws_copy_policy-23.12.2.dist-info/RECORD
