Metadata-Version: 2.1
Name: ws-copy-policy
Version: 23.12.2
Summary: WS Copy Policy
Home-page: https://github.com/whitesource-ps/ws-copy-policy
Author: Mend Professional Services
Author-email: ps@whitesourcesoftware.com
License: LICENSE
Platform: UNKNOWN
Classifier: Programming Language :: Python :: 3.9
Classifier: Programming Language :: Python :: 3.10
Classifier: Programming Language :: Python :: 3.11
Classifier: License :: OSI Approved :: Apache Software License
Classifier: Operating System :: OS Independent
Requires-Python: >=3.9
License-File: LICENSE
Requires-Dist: configparser ~=5.3.0
Requires-Dist: requests ~=2.28.1
